picklecachefunc/__init__.py
picklecachefunc/picklecachefunc.py
tests/__init__.py
tests/test_picklecachefunc.py
picklecachefunc-0.6.0.dist-info/LICENSE
picklecachefunc-0.6.0.dist-info/METADATA
picklecachefunc-0.6.0.dist-info/WHEEL
picklecachefunc-0.6.0.dist-info/top_level.txt
picklecachefunc-0.6.0.dist-info/RECORD
