Metadata-Version: 2.1
Name: picklecachefunc
Version: 0.6.0
Summary: A decorator to cache function outputs to files using pickle.
Home-page: https://github.com/coallaoh/picklecachefunc
Author: Seong Joon Oh
Author-email: coallaoh@gmail.com
License: MIT
Platform: UNKNOWN
Classifier: Programming Language :: Python :: 3
Classifier: License :: OSI Approved :: MIT License
Classifier: Operating System :: OS Independent
Requires-Python: >=3.6
